resources/99-eyes17-pip.rules
resources/__init__.py
resources/sispmctl.conf
seelab_examples/AudioCharacteristics.py
seelab_examples/BHCurve.py
seelab_examples/BHCurveHMC.py
seelab_examples/Communications.py
seelab_examples/Communications_freq.py
seelab_examples/Counter.py
seelab_examples/DCOhmsLaw.py
seelab_examples/DrivenPendulum.py
seelab_examples/DualDrivenPendulum.py
seelab_examples/FilterCharacteristics.py
seelab_examples/InternetOfThings.py
seelab_examples/LemonCell.py
seelab_examples/MPU6050.py
seelab_examples/MeasureCapacitance.py
seelab_examples/MeasureResistance.py
seelab_examples/QtVersion.py
seelab_examples/RCtransient.py
seelab_examples/RLCsteadystate.py
seelab_examples/RLCtransient.py
seelab_examples/RLtransient.py
seelab_examples/SensorLogger1.py
seelab_examples/SimpleDiodeIV.py
seelab_examples/TimeOfFlight.py
seelab_examples/Timings.py
seelab_examples/VisualCoding.py
seelab_examples/XYPlotContinuous.py
seelab_examples/XYplot.py
seelab_examples/XYplot2.py
seelab_examples/__init__.py
seelab_examples/__main__.py
seelab_examples/advanced_logger.py
seelab_examples/advanced_logger_pe.py
seelab_examples/calibrator.py
seelab_examples/circuitjs.py
seelab_examples/data_logger.py
seelab_examples/diodeIV.py
seelab_examples/drivenRodPendulum.py
seelab_examples/dust_sensor.py
seelab_examples/experiments.json
seelab_examples/filterCircuit.py
seelab_examples/i2cLogger.py
seelab_examples/induction.py
seelab_examples/ipy.py
seelab_examples/lightsensorlogger.py
seelab_examples/logger.py
seelab_examples/magnetic_field_visualizer.py
seelab_examples/magnetic_gradient.py
seelab_examples/measureDC.py
seelab_examples/measureKneeVoltage.py
seelab_examples/multiplexedlogger.py
seelab_examples/mycode.py
seelab_examples/new.py
seelab_examples/npnCEout.py
seelab_examples/oscilloscope.py
seelab_examples/pendulumVelocity.py
seelab_examples/plotIV.py
seelab_examples/pnpCEout.py
seelab_examples/pt100.py
seelab_examples/rodPendulum.py
seelab_examples/schoolscope.py
seelab_examples-1.4.2.dist-info/METADATA
seelab_examples-1.4.2.dist-info/WHEEL
seelab_examples-1.4.2.dist-info/entry_points.txt
seelab_examples-1.4.2.dist-info/top_level.txt
seelab_examples-1.4.2.dist-info/RECORD
