Metadata-Version: 2.1
Name: seelab-examples
Version: 1.4.2
Summary: Python package for SEELab3 and ExpEYES17 Examples
Home-page: https://github.com/csparkresearch/seelab3
Author: Jithin B.P
Author-email: jithinbp@gmail.com
License: UNKNOWN
Project-URL: Source, https://github.com/expeyes/expeyes-programs
Project-URL: Read The Docs, https://eyes17lib.readthedocs.io
Project-URL: Buy Hardware, https://csparkresearch.in/seelab3
Keywords: SEELab3 ExpEYES17 data-acquisition oscilloscope
Platform: UNKNOWN
Classifier: Development Status :: 5 - Production/Stable
Classifier: Intended Audience :: Education
Classifier: Programming Language :: Python :: 3
Classifier: License :: OSI Approved :: MIT License
Classifier: Operating System :: OS Independent
Requires-Python: >=3
Requires-Dist: eyes17lib
Requires-Dist: numpy
Requires-Dist: pyopengl
Requires-Dist: pyqt5
Requires-Dist: pyqtgraph
Requires-Dist: pyserial
Requires-Dist: qtconsole
Requires-Dist: requests
Requires-Dist: scipy
Requires-Dist: simple-pid
Requires-Dist: webserver
